GenCareAIUtils/__init__.py
GenCareAIUtils-0.2.3.dist-info/LICENSE
GenCareAIUtils-0.2.3.dist-info/METADATA
GenCareAIUtils-0.2.3.dist-info/WHEEL
GenCareAIUtils-0.2.3.dist-info/top_level.txt
GenCareAIUtils-0.2.3.dist-info/RECORD
