Metadata-Version: 2.1
Name: GenCareAIUtils
Version: 0.2.3
Summary: Helper functions for the GenCareAI project
Home-page: https://github.com/ekrombouts/GenCareAIUtils
Author: Eva Rombouts
Author-email: info@doktereva.nl
License-File: LICENSE
Requires-Dist: python-dotenv
